pmc_automation_tools/__init__.py
pmc_automation_tools/api/__init__.py
pmc_automation_tools/api/common.py
pmc_automation_tools/api/datasource.py
pmc_automation_tools/api/classic/__init__.py
pmc_automation_tools/api/classic/datasource.py
pmc_automation_tools/api/ux/__init__.py
pmc_automation_tools/api/ux/datasource.py
pmc_automation_tools/common/__init__.py
pmc_automation_tools/common/exceptions.py
pmc_automation_tools/common/utils.py
pmc_automation_tools/driver/__init__.py
pmc_automation_tools/driver/common.py
pmc_automation_tools/driver/generic.py
pmc_automation_tools/driver/classic/__init__.py
pmc_automation_tools/driver/classic/driver.py
pmc_automation_tools/driver/ux/__init__.py
pmc_automation_tools/driver/ux/driver.py
pmc_automation_tools-0.6.4.dist-info/METADATA
pmc_automation_tools-0.6.4.dist-info/WHEEL
pmc_automation_tools-0.6.4.dist-info/licenses/LICENSE
pmc_automation_tools-0.6.4.dist-info/RECORD
