Metadata-Version: 2.3
Name: pmc-automation-tools
Version: 0.6.4
Summary: A collection of tools to help automate Plex Manufacturing Cloud activities.
Project-URL: Homepage, https://github.com/DanSleeman/PMC_Automation_Tools
Project-URL: Issues, https://github.com/DanSleeman/PMC_Automation_Tools/Issues
Author-email: Dan Sleeman <dansleeman@gmail.com>
License-File: LICENSE
Classifier: License :: OSI Approved :: GNU General Public License v3 (GPLv3)
Classifier: Operating System :: OS Independent
Classifier: Programming Language :: Python :: 3
Classifier: Topic :: Utilities
Requires-Python: >=3.8
Requires-Dist: openpyxl>=3.1.5
Requires-Dist: requests>=2.31.0
Requires-Dist: selenium>=4.13.0
Requires-Dist: urllib3>=2.0.6
Requires-Dist: zeep>=4.2.1
